g3shvnodes/__init__.py
g3shvnodes/py.typed
g3shvnodes/all/__init__.py
g3shvnodes/cabinet/__init__.py
g3shvnodes/cabinet/_control.py
g3shvnodes/cabinet/_test.py
g3shvnodes/cli/__init__.py
g3shvnodes/cli/_parse_status.py
g3shvnodes/detector/__init__.py
g3shvnodes/detector/_control.py
g3shvnodes/detector/_test.py
g3shvnodes/gate/__init__.py
g3shvnodes/gate/_control.py
g3shvnodes/gate/_test.py
g3shvnodes/gpio/__init__.py
g3shvnodes/gpio/_control.py
g3shvnodes/gpio/_test.py
g3shvnodes/heating/__init__.py
g3shvnodes/heating/_control.py
g3shvnodes/heating/_test.py
g3shvnodes/node/__init__.py
g3shvnodes/node/_node.py
g3shvnodes/pointmachine/__init__.py
g3shvnodes/pointmachine/_control.py
g3shvnodes/pointmachine/_test.py
g3shvnodes/requestor/__init__.py
g3shvnodes/requestor/_control.py
g3shvnodes/requestor/_test.py
g3shvnodes/route/__init__.py
g3shvnodes/route/_control.py
g3shvnodes/route/_test.py
g3shvnodes/signal/__init__.py
g3shvnodes/signal/_control.py
g3shvnodes/signal/_test.py
g3shvnodes/system/__init__.py
g3shvnodes/system/_control.py
g3shvnodes/system/_test.py
g3shvnodes/zone/__init__.py
g3shvnodes/zone/_control.py
g3shvnodes/zone/_test.py
g3shvnodes-0.1.0.dist-info/LICENCE
g3shvnodes-0.1.0.dist-info/METADATA
g3shvnodes-0.1.0.dist-info/WHEEL
g3shvnodes-0.1.0.dist-info/entry_points.txt
g3shvnodes-0.1.0.dist-info/top_level.txt
g3shvnodes-0.1.0.dist-info/RECORD
