Metadata-Version: 2.1
Name: g3shvnodes
Version: 0.1.0
Summary: PLC System G3 SHV Nodes
Author: Elektroline a.s.
Project-URL: Homepage, https://gitlab.elektroline.cz/plc/systemg3-py/SystemG3SHVNodes
Keywords: Elektroline,System G3
Classifier: Development Status :: 3 - Alpha
Classifier: Intended Audience :: Developers
Classifier: Intended Audience :: Other Audience
Classifier: License :: OSI Approved :: MIT License
Classifier: Natural Language :: English
Classifier: Operating System :: OS Independent
Classifier: Programming Language :: Python :: 3
Classifier: Programming Language :: Python :: 3 :: Only
Classifier: Programming Language :: Python :: 3.10
Classifier: Programming Language :: Python :: 3.11
Classifier: Programming Language :: Python :: 3.12
Classifier: Topic :: Software Development :: Libraries :: Python Modules
Classifier: Typing :: Typed
Requires-Python: >=3.11
License-File: LICENCE
Requires-Dist: pyshv ==0.6.1
Provides-Extra: cli
Requires-Dist: rich ; extra == 'cli'
Provides-Extra: docs
Requires-Dist: sphinx ; extra == 'docs'
Requires-Dist: sphinx-rtd-theme ; extra == 'docs'
Provides-Extra: test
Requires-Dist: pytest ; extra == 'test'
Requires-Dist: pytest-asyncio ==0.21.1 ; extra == 'test'
